{
	"start":	{
		"connected":	[{
				"socket":	5,
				"local_host":	"192.168.253.128",
				"local_port":	42268,
				"remote_host":	"128.143.71.13",
				"remote_port":	5201
			}],
		"version":	"iperf 3.9",
		"system_info":	"Linux uva-os-vm 5.15.0-161-generic #171-Ubuntu SMP Sat Oct 11 08:27:25 UTC 2025 aarch64",
		"timestamp":	{
			"time":	"Mon, 08 Dec 2025 01:16:13 GMT",
			"timesecs":	1765156573
		},
		"connecting_to":	{
			"host":	"128.143.71.13",
			"port":	5201
		},
		"cookie":	"g5nz5gn7fuy2h6krvxyzeqmtf7cq5nsooxua",
		"tcp_mss_default":	1460,
		"sock_bufsize":	0,
		"sndbuf_actual":	67108864,
		"rcvbuf_actual":	67108864,
		"test_start":	{
			"protocol":	"TCP",
			"num_streams":	1,
			"blksize":	131072,
			"omit":	0,
			"duration":	30,
			"bytes":	0,
			"blocks":	0,
			"reverse":	0,
			"tos":	0
		}
	},
	"intervals":	[{
			"streams":	[{
					"socket":	5,
					"start":	0,
					"end":	0.500302,
					"seconds":	0.500302016735077,
					"bytes":	44564480,
					"bits_per_second":	712601244.99714839,
					"retransmits":	0,
					"snd_cwnd":	129940,
					"rtt":	52103,
					"rttvar":	57,
					"pmtu":	1500,
					"omitted":	false,
					"sender":	true
				}],
			"sum":	{
				"start":	0,
				"end":	0.500302,
				"seconds":	0.500302016735077,
				"bytes":	44564480,
				"bits_per_second":	712601244.99714839,
				"retransmits":	0,
				"omitted":	false,
				"sender":	true
			}
		}, {
			"streams":	[{
					"socket":	5,
					"start":	0.500302,
					"end":	1.000582,
					"seconds":	0.50028002262115479,
					"bytes":	0,
					"bits_per_second":	0,
					"retransmits":	0,
					"snd_cwnd":	144540,
					"rtt":	51719,
					"rttvar":	487,
					"pmtu":	1500,
					"omitted":	false,
					"sender":	true
				}],
			"sum":	{
				"start":	0.500302,
				"end":	1.000582,
				"seconds":	0.50028002262115479,
				"bytes":	0,
				"bits_per_second":	0,
				"retransmits":	0,
				"omitted":	false,
				"sender":	true
			}
		}, {
			"streams":	[{
					"socket":	5,
					"start":	1.000582,
					"end":	1.500573,
					"seconds":	0.49999099969863892,
					"bytes":	1310720,
					"bits_per_second":	20971897.50679535,
					"retransmits":	0,
					"snd_cwnd":	157680,
					"rtt":	51782,
					"rttvar":	217,
					"pmtu":	1500,
					"omitted":	false,
					"sender":	true
				}],
			"sum":	{
				"start":	1.000582,
				"end":	1.500573,
				"seconds":	0.49999099969863892,
				"bytes":	1310720,
				"bits_per_second":	20971897.50679535,
				"retransmits":	0,
				"omitted":	false,
				"sender":	true
			}
		}, {
			"streams":	[{
					"socket":	5,
					"start":	1.500573,
					"end":	2.018087,
					"seconds":	0.51751399040222168,
					"bytes":	0,
					"bits_per_second":	0,
					"retransmits":	0,
					"snd_cwnd":	170820,
					"rtt":	68625,
					"rttvar":	947,
					"pmtu":	1500,
					"omitted":	false,
					"sender":	true
				}],
			"sum":	{
				"start":	1.500573,
				"end":	2.018087,
				"seconds":	0.51751399040222168,
				"bytes":	0,
				"bits_per_second":	0,
				"retransmits":	0,
				"omitted":	false,
				"sender":	true
			}
		}, {
			"streams":	[{
					"socket":	5,
					"start":	2.018087,
					"end":	2.511241,
					"seconds":	0.493153989315033,
					"bytes":	1310720,
					"bits_per_second":	21262648.639554176,
					"retransmits":	0,
					"snd_cwnd":	183960,
					"rtt":	54454,
					"rttvar":	4242,
					"pmtu":	1500,
					"omitted":	false,
					"sender":	true
				}],
			"sum":	{
				"start":	2.018087,
				"end":	2.511241,
				"seconds":	0.493153989315033,
				"bytes":	1310720,
				"bits_per_second":	21262648.639554176,
				"retransmits":	0,
				"omitted":	false,
				"sender":	true
			}
		}, {
			"streams":	[{
					"socket":	5,
					"start":	2.511241,
					"end":	3.002176,
					"seconds":	0.49093499779701233,
					"bytes":	0,
					"bits_per_second":	0,
					"retransmits":	0,
					"snd_cwnd":	197100,
					"rtt":	51824,
					"rttvar":	843,
					"pmtu":	1500,
					"omitted":	false,
					"sender":	true
				}],
			"sum":	{
				"start":	2.511241,
				"end":	3.002176,
				"seconds":	0.49093499779701233,
				"bytes":	0,
				"bits_per_second":	0,
				"retransmits":	0,
				"omitted":	false,
				"sender":	true
			}
		}, {
			"streams":	[{
					"socket":	5,
					"start":	3.002176,
					"end":	3.500865,
					"seconds":	0.49868899583816528,
					"bytes":	0,
					"bits_per_second":	0,
					"retransmits":	0,
					"snd_cwnd":	211700,
					"rtt":	50476,
					"rttvar":	62,
					"pmtu":	1500,
					"omitted":	false,
					"sender":	true
				}],
			"sum":	{
				"start":	3.002176,
				"end":	3.500865,
				"seconds":	0.49868899583816528,
				"bytes":	0,
				"bits_per_second":	0,
				"retransmits":	0,
				"omitted":	false,
				"sender":	true
			}
		}, {
			"streams":	[{
					"socket":	5,
					"start":	3.500865,
					"end":	4.000914,
					"seconds":	0.50004899501800537,
					"bytes":	1310720,
					"bits_per_second":	20969465.2013498,
					"retransmits":	0,
					"snd_cwnd":	226300,
					"rtt":	51616,
					"rttvar":	65,
					"pmtu":	1500,
					"omitted":	false,
					"sender":	true
				}],
			"sum":	{
				"start":	3.500865,
				"end":	4.000914,
				"seconds":	0.50004899501800537,
				"bytes":	1310720,
				"bits_per_second":	20969465.2013498,
				"retransmits":	0,
				"omitted":	false,
				"sender":	true
			}
		}, {
			"streams":	[{
					"socket":	5,
					"start":	4.000914,
					"end":	4.501236,
					"seconds":	0.50032198429107666,
					"bytes":	0,
					"bits_per_second":	0,
					"retransmits":	0,
					"snd_cwnd":	240900,
					"rtt":	51144,
					"rttvar":	100,
					"pmtu":	1500,
					"omitted":	false,
					"sender":	true
				}],
			"sum":	{
				"start":	4.000914,
				"end":	4.501236,
				"seconds":	0.50032198429107666,
				"bytes":	0,
				"bits_per_second":	0,
				"retransmits":	0,
				"omitted":	false,
				"sender":	true
			}
		}, {
			"streams":	[{
					"socket":	5,
					"start":	4.501236,
					"end":	5.000712,
					"seconds":	0.49947598576545715,
					"bytes":	1310720,
					"bits_per_second":	20993521.8085217,
					"retransmits":	0,
					"snd_cwnd":	254040,
					"rtt":	50727,
					"rttvar":	82,
					"pmtu":	1500,
					"omitted":	false,
					"sender":	true
				}],
			"sum":	{
				"start":	4.501236,
				"end":	5.000712,
				"seconds":	0.49947598576545715,
				"bytes":	1310720,
				"bits_per_second":	20993521.8085217,
				"retransmits":	0,
				"omitted":	false,
				"sender":	true
			}
		}, {
			"streams":	[{
					"socket":	5,
					"start":	5.000712,
					"end":	5.500651,
					"seconds":	0.49993899464607239,
					"bytes":	0,
					"bits_per_second":	0,
					"retransmits":	0,
					"snd_cwnd":	268640,
					"rtt":	58943,
					"rttvar":	6108,
					"pmtu":	1500,
					"omitted":	false,
					"sender":	true
				}],
			"sum":	{
				"start":	5.000712,
				"end":	5.500651,
				"seconds":	0.49993899464607239,
				"bytes":	0,
				"bits_per_second":	0,
				"retransmits":	0,
				"omitted":	false,
				"sender":	true
			}
		}, {
			"streams":	[{
					"socket":	5,
					"start":	5.500651,
					"end":	6.000559,
					"seconds":	0.49990800023078918,
					"bytes":	1310720,
					"bits_per_second":	20975379.460138883,
					"retransmits":	0,
					"snd_cwnd":	281780,
					"rtt":	50703,
					"rttvar":	84,
					"pmtu":	1500,
					"omitted":	false,
					"sender":	true
				}],
			"sum":	{
				"start":	5.500651,
				"end":	6.000559,
				"seconds":	0.49990800023078918,
				"bytes":	1310720,
				"bits_per_second":	20975379.460138883,
				"retransmits":	0,
				"omitted":	false,
				"sender":	true
			}
		}, {
			"streams":	[{
					"socket":	5,
					"start":	6.000559,
					"end":	6.500721,
					"seconds":	0.50016200542449951,
					"bytes":	0,
					"bits_per_second":	0,
					"retransmits":	0,
					"snd_cwnd":	296380,
					"rtt":	51291,
					"rttvar":	115,
					"pmtu":	1500,
					"omitted":	false,
					"sender":	true
				}],
			"sum":	{
				"start":	6.000559,
				"end":	6.500721,
				"seconds":	0.50016200542449951,
				"bytes":	0,
				"bits_per_second":	0,
				"retransmits":	0,
				"omitted":	false,
				"sender":	true
			}
		}, {
			"streams":	[{
					"socket":	5,
					"start":	6.500721,
					"end":	7.000628,
					"seconds":	0.499906986951828,
					"bytes":	1310720,
					"bits_per_second":	20975421.975869339,
					"retransmits":	0,
					"snd_cwnd":	303680,
					"rtt":	50823,
					"rttvar":	131,
					"pmtu":	1500,
					"omitted":	false,
					"sender":	true
				}],
			"sum":	{
				"start":	6.500721,
				"end":	7.000628,
				"seconds":	0.499906986951828,
				"bytes":	1310720,
				"bits_per_second":	20975421.975869339,
				"retransmits":	0,
				"omitted":	false,
				"sender":	true
			}
		}, {
			"streams":	[{
					"socket":	5,
					"start":	7.000628,
					"end":	7.501399,
					"seconds":	0.50077098608016968,
					"bytes":	0,
					"bits_per_second":	0,
					"retransmits":	0,
					"snd_cwnd":	315360,
					"rtt":	51053,
					"rttvar":	111,
					"pmtu":	1500,
					"omitted":	false,
					"sender":	true
				}],
			"sum":	{
				"start":	7.000628,
				"end":	7.501399,
				"seconds":	0.50077098608016968,
				"bytes":	0,
				"bits_per_second":	0,
				"retransmits":	0,
				"omitted":	false,
				"sender":	true
			}
		}, {
			"streams":	[{
					"socket":	5,
					"start":	7.501399,
					"end":	8.000516,
					"seconds":	0.499116986989975,
					"bytes":	1310720,
					"bits_per_second":	21008621.77269597,
					"retransmits":	0,
					"snd_cwnd":	328500,
					"rtt":	52364,
					"rttvar":	363,
					"pmtu":	1500,
					"omitted":	false,
					"sender":	true
				}],
			"sum":	{
				"start":	7.501399,
				"end":	8.000516,
				"seconds":	0.499116986989975,
				"bytes":	1310720,
				"bits_per_second":	21008621.77269597,
				"retransmits":	0,
				"omitted":	false,
				"sender":	true
			}
		}, {
			"streams":	[{
					"socket":	5,
					"start":	8.000516,
					"end":	8.500784,
					"seconds":	0.50026798248291,
					"bytes":	0,
					"bits_per_second":	0,
					"retransmits":	0,
					"snd_cwnd":	341640,
					"rtt":	50513,
					"rttvar":	120,
					"pmtu":	1500,
					"omitted":	false,
					"sender":	true
				}],
			"sum":	{
				"start":	8.000516,
				"end":	8.500784,
				"seconds":	0.50026798248291,
				"bytes":	0,
				"bits_per_second":	0,
				"retransmits":	0,
				"omitted":	false,
				"sender":	true
			}
		}, {
			"streams":	[{
					"socket":	5,
					"start":	8.500784,
					"end":	9.000536,
					"seconds":	0.499752014875412,
					"bytes":	1310720,
					"bits_per_second":	20981926.411270391,
					"retransmits":	0,
					"snd_cwnd":	356240,
					"rtt":	51336,
					"rttvar":	150,
					"pmtu":	1500,
					"omitted":	false,
					"sender":	true
				}],
			"sum":	{
				"start":	8.500784,
				"end":	9.000536,
				"seconds":	0.499752014875412,
				"bytes":	1310720,
				"bits_per_second":	20981926.411270391,
				"retransmits":	0,
				"omitted":	false,
				"sender":	true
			}
		}, {
			"streams":	[{
					"socket":	5,
					"start":	9.000536,
					"end":	9.500726,
					"seconds":	0.500190019607544,
					"bytes":	0,
					"bits_per_second":	0,
					"retransmits":	0,
					"snd_cwnd":	365000,
					"rtt":	51133,
					"rttvar":	132,
					"pmtu":	1500,
					"omitted":	false,
					"sender":	true
				}],
			"sum":	{
				"start":	9.000536,
				"end":	9.500726,
				"seconds":	0.500190019607544,
				"bytes":	0,
				"bits_per_second":	0,
				"retransmits":	0,
				"omitted":	false,
				"sender":	true
			}
		}, {
			"streams":	[{
					"socket":	5,
					"start":	9.500726,
					"end":	10.000303,
					"seconds":	0.499576985836029,
					"bytes":	1310720,
					"bits_per_second":	20989277.5233678,
					"retransmits":	0,
					"snd_cwnd":	373760,
					"rtt":	50625,
					"rttvar":	95,
					"pmtu":	1500,
					"omitted":	false,
					"sender":	true
				}],
			"sum":	{
				"start":	9.500726,
				"end":	10.000303,
				"seconds":	0.499576985836029,
				"bytes":	1310720,
				"bits_per_second":	20989277.5233678,
				"retransmits":	0,
				"omitted":	false,
				"sender":	true
			}
		}, {
			"streams":	[{
					"socket":	5,
					"start":	10.000303,
					"end":	10.500876,
					"seconds":	0.50057297945022583,
					"bytes":	0,
					"bits_per_second":	0,
					"retransmits":	0,
					"snd_cwnd":	385440,
					"rtt":	51169,
					"rttvar":	190,
					"pmtu":	1500,
					"omitted":	false,
					"sender":	true
				}],
			"sum":	{
				"start":	10.000303,
				"end":	10.500876,
				"seconds":	0.50057297945022583,
				"bytes":	0,
				"bits_per_second":	0,
				"retransmits":	0,
				"omitted":	false,
				"sender":	true
			}
		}, {
			"streams":	[{
					"socket":	5,
					"start":	10.500876,
					"end":	11.00052,
					"seconds":	0.499644011259079,
					"bytes":	1310720,
					"bits_per_second":	20986461.888288,
					"retransmits":	0,
					"snd_cwnd":	397120,
					"rtt":	50950,
					"rttvar":	279,
					"pmtu":	1500,
					"omitted":	false,
					"sender":	true
				}],
			"sum":	{
				"start":	10.500876,
				"end":	11.00052,
				"seconds":	0.499644011259079,
				"bytes":	1310720,
				"bits_per_second":	20986461.888288,
				"retransmits":	0,
				"omitted":	false,
				"sender":	true
			}
		}, {
			"streams":	[{
					"socket":	5,
					"start":	11.00052,
					"end":	11.500664,
					"seconds":	0.50014400482177734,
					"bytes":	0,
					"bits_per_second":	0,
					"retransmits":	0,
					"snd_cwnd":	408800,
					"rtt":	51080,
					"rttvar":	174,
					"pmtu":	1500,
					"omitted":	false,
					"sender":	true
				}],
			"sum":	{
				"start":	11.00052,
				"end":	11.500664,
				"seconds":	0.50014400482177734,
				"bytes":	0,
				"bits_per_second":	0,
				"retransmits":	0,
				"omitted":	false,
				"sender":	true
			}
		}, {
			"streams":	[{
					"socket":	5,
					"start":	11.500664,
					"end":	12.000872,
					"seconds":	0.500208020210266,
					"bytes":	1310720,
					"bits_per_second":	20962798.628443088,
					"retransmits":	0,
					"snd_cwnd":	421940,
					"rtt":	50705,
					"rttvar":	109,
					"pmtu":	1500,
					"omitted":	false,
					"sender":	true
				}],
			"sum":	{
				"start":	11.500664,
				"end":	12.000872,
				"seconds":	0.500208020210266,
				"bytes":	1310720,
				"bits_per_second":	20962798.628443088,
				"retransmits":	0,
				"omitted":	false,
				"sender":	true
			}
		}, {
			"streams":	[{
					"socket":	5,
					"start":	12.000872,
					"end":	12.500579,
					"seconds":	0.49970701336860657,
					"bytes":	0,
					"bits_per_second":	0,
					"retransmits":	0,
					"snd_cwnd":	432160,
					"rtt":	51404,
					"rttvar":	205,
					"pmtu":	1500,
					"omitted":	false,
					"sender":	true
				}],
			"sum":	{
				"start":	12.000872,
				"end":	12.500579,
				"seconds":	0.49970701336860657,
				"bytes":	0,
				"bits_per_second":	0,
				"retransmits":	0,
				"omitted":	false,
				"sender":	true
			}
		}, {
			"streams":	[{
					"socket":	5,
					"start":	12.500579,
					"end":	13.000263,
					"seconds":	0.49968400597572327,
					"bytes":	1310720,
					"bits_per_second":	20984782.131508611,
					"retransmits":	0,
					"snd_cwnd":	442380,
					"rtt":	50760,
					"rttvar":	176,
					"pmtu":	1500,
					"omitted":	false,
					"sender":	true
				}],
			"sum":	{
				"start":	12.500579,
				"end":	13.000263,
				"seconds":	0.49968400597572327,
				"bytes":	1310720,
				"bits_per_second":	20984782.131508611,
				"retransmits":	0,
				"omitted":	false,
				"sender":	true
			}
		}, {
			"streams":	[{
					"socket":	5,
					"start":	13.000263,
					"end":	13.500849,
					"seconds":	0.500585973262787,
					"bytes":	0,
					"bits_per_second":	0,
					"retransmits":	0,
					"snd_cwnd":	452600,
					"rtt":	51075,
					"rttvar":	268,
					"pmtu":	1500,
					"omitted":	false,
					"sender":	true
				}],
			"sum":	{
				"start":	13.000263,
				"end":	13.500849,
				"seconds":	0.500585973262787,
				"bytes":	0,
				"bits_per_second":	0,
				"retransmits":	0,
				"omitted":	false,
				"sender":	true
			}
		}, {
			"streams":	[{
					"socket":	5,
					"start":	13.500849,
					"end":	14.000652,
					"seconds":	0.49980300664901733,
					"bytes":	0,
					"bits_per_second":	0,
					"retransmits":	0,
					"snd_cwnd":	464280,
					"rtt":	51166,
					"rttvar":	194,
					"pmtu":	1500,
					"omitted":	false,
					"sender":	true
				}],
			"sum":	{
				"start":	13.500849,
				"end":	14.000652,
				"seconds":	0.49980300664901733,
				"bytes":	0,
				"bits_per_second":	0,
				"retransmits":	0,
				"omitted":	false,
				"sender":	true
			}
		}, {
			"streams":	[{
					"socket":	5,
					"start":	14.000652,
					"end":	14.500565,
					"seconds":	0.49991300702095032,
					"bytes":	1310720,
					"bits_per_second":	20975169.384941734,
					"retransmits":	0,
					"snd_cwnd":	477420,
					"rtt":	51209,
					"rttvar":	232,
					"pmtu":	1500,
					"omitted":	false,
					"sender":	true
				}],
			"sum":	{
				"start":	14.000652,
				"end":	14.500565,
				"seconds":	0.49991300702095032,
				"bytes":	1310720,
				"bits_per_second":	20975169.384941734,
				"retransmits":	0,
				"omitted":	false,
				"sender":	true
			}
		}, {
			"streams":	[{
					"socket":	5,
					"start":	14.500565,
					"end":	15.000589,
					"seconds":	0.50002402067184448,
					"bytes":	0,
					"bits_per_second":	0,
					"retransmits":	0,
					"snd_cwnd":	490560,
					"rtt":	50982,
					"rttvar":	211,
					"pmtu":	1500,
					"omitted":	false,
					"sender":	true
				}],
			"sum":	{
				"start":	14.500565,
				"end":	15.000589,
				"seconds":	0.50002402067184448,
				"bytes":	0,
				"bits_per_second":	0,
				"retransmits":	0,
				"omitted":	false,
				"sender":	true
			}
		}, {
			"streams":	[{
					"socket":	5,
					"start":	15.000589,
					"end":	15.501023,
					"seconds":	0.50043398141860962,
					"bytes":	1310720,
					"bits_per_second":	20953333.285392411,
					"retransmits":	0,
					"snd_cwnd":	505160,
					"rtt":	50956,
					"rttvar":	201,
					"pmtu":	1500,
					"omitted":	false,
					"sender":	true
				}],
			"sum":	{
				"start":	15.000589,
				"end":	15.501023,
				"seconds":	0.50043398141860962,
				"bytes":	1310720,
				"bits_per_second":	20953333.285392411,
				"retransmits":	0,
				"omitted":	false,
				"sender":	true
			}
		}, {
			"streams":	[{
					"socket":	5,
					"start":	15.501023,
					"end":	16.001534,
					"seconds":	0.50051099061965942,
					"bytes":	0,
					"bits_per_second":	0,
					"retransmits":	0,
					"snd_cwnd":	513920,
					"rtt":	51641,
					"rttvar":	118,
					"pmtu":	1500,
					"omitted":	false,
					"sender":	true
				}],
			"sum":	{
				"start":	15.501023,
				"end":	16.001534,
				"seconds":	0.50051099061965942,
				"bytes":	0,
				"bits_per_second":	0,
				"retransmits":	0,
				"omitted":	false,
				"sender":	true
			}
		}, {
			"streams":	[{
					"socket":	5,
					"start":	16.001534,
					"end":	16.500566,
					"seconds":	0.49903199076652527,
					"bytes":	1310720,
					"bits_per_second":	21012200.007245261,
					"retransmits":	0,
					"snd_cwnd":	527060,
					"rtt":	50825,
					"rttvar":	383,
					"pmtu":	1500,
					"omitted":	false,
					"sender":	true
				}],
			"sum":	{
				"start":	16.001534,
				"end":	16.500566,
				"seconds":	0.49903199076652527,
				"bytes":	1310720,
				"bits_per_second":	21012200.007245261,
				"retransmits":	0,
				"omitted":	false,
				"sender":	true
			}
		}, {
			"streams":	[{
					"socket":	5,
					"start":	16.500566,
					"end":	17.001483,
					"seconds":	0.50091701745986938,
					"bytes":	0,
					"bits_per_second":	0,
					"retransmits":	0,
					"snd_cwnd":	535820,
					"rtt":	51308,
					"rttvar":	266,
					"pmtu":	1500,
					"omitted":	false,
					"sender":	true
				}],
			"sum":	{
				"start":	16.500566,
				"end":	17.001483,
				"seconds":	0.50091701745986938,
				"bytes":	0,
				"bits_per_second":	0,
				"retransmits":	0,
				"omitted":	false,
				"sender":	true
			}
		}, {
			"streams":	[{
					"socket":	5,
					"start":	17.001483,
					"end":	17.500539,
					"seconds":	0.49905601143836975,
					"bytes":	1310720,
					"bits_per_second":	21011188.643491421,
					"retransmits":	0,
					"snd_cwnd":	548960,
					"rtt":	50862,
					"rttvar":	90,
					"pmtu":	1500,
					"omitted":	false,
					"sender":	true
				}],
			"sum":	{
				"start":	17.001483,
				"end":	17.500539,
				"seconds":	0.49905601143836975,
				"bytes":	1310720,
				"bits_per_second":	21011188.643491421,
				"retransmits":	0,
				"omitted":	false,
				"sender":	true
			}
		}, {
			"streams":	[{
					"socket":	5,
					"start":	17.500539,
					"end":	18.000987,
					"seconds":	0.500447988510132,
					"bytes":	0,
					"bits_per_second":	0,
					"retransmits":	0,
					"snd_cwnd":	562100,
					"rtt":	51173,
					"rttvar":	99,
					"pmtu":	1500,
					"omitted":	false,
					"sender":	true
				}],
			"sum":	{
				"start":	17.500539,
				"end":	18.000987,
				"seconds":	0.500447988510132,
				"bytes":	0,
				"bits_per_second":	0,
				"retransmits":	0,
				"omitted":	false,
				"sender":	true
			}
		}, {
			"streams":	[{
					"socket":	5,
					"start":	18.000987,
					"end":	18.500358,
					"seconds":	0.4993709921836853,
					"bytes":	1310720,
					"bits_per_second":	20997935.731403053,
					"retransmits":	0,
					"snd_cwnd":	572320,
					"rtt":	50716,
					"rttvar":	24,
					"pmtu":	1500,
					"omitted":	false,
					"sender":	true
				}],
			"sum":	{
				"start":	18.000987,
				"end":	18.500358,
				"seconds":	0.4993709921836853,
				"bytes":	1310720,
				"bits_per_second":	20997935.731403053,
				"retransmits":	0,
				"omitted":	false,
				"sender":	true
			}
		}, {
			"streams":	[{
					"socket":	5,
					"start":	18.500358,
					"end":	19.002444,
					"seconds":	0.50208598375320435,
					"bytes":	0,
					"bits_per_second":	0,
					"retransmits":	0,
					"snd_cwnd":	584000,
					"rtt":	51792,
					"rttvar":	278,
					"pmtu":	1500,
					"omitted":	false,
					"sender":	true
				}],
			"sum":	{
				"start":	18.500358,
				"end":	19.002444,
				"seconds":	0.50208598375320435,
				"bytes":	0,
				"bits_per_second":	0,
				"retransmits":	0,
				"omitted":	false,
				"sender":	true
			}
		}, {
			"streams":	[{
					"socket":	5,
					"start":	19.002444,
					"end":	19.500399,
					"seconds":	0.49795499444007874,
					"bytes":	1310720,
					"bits_per_second":	21057646.006323572,
					"retransmits":	0,
					"snd_cwnd":	585460,
					"rtt":	50873,
					"rttvar":	65,
					"pmtu":	1500,
					"omitted":	false,
					"sender":	true
				}],
			"sum":	{
				"start":	19.002444,
				"end":	19.500399,
				"seconds":	0.49795499444007874,
				"bytes":	1310720,
				"bits_per_second":	21057646.006323572,
				"retransmits":	0,
				"omitted":	false,
				"sender":	true
			}
		}, {
			"streams":	[{
					"socket":	5,
					"start":	19.500399,
					"end":	20.000836,
					"seconds":	0.500437021255493,
					"bytes":	0,
					"bits_per_second":	0,
					"retransmits":	0,
					"snd_cwnd":	585460,
					"rtt":	51929,
					"rttvar":	537,
					"pmtu":	1500,
					"omitted":	false,
					"sender":	true
				}],
			"sum":	{
				"start":	19.500399,
				"end":	20.000836,
				"seconds":	0.500437021255493,
				"bytes":	0,
				"bits_per_second":	0,
				"retransmits":	0,
				"omitted":	false,
				"sender":	true
			}
		}, {
			"streams":	[{
					"socket":	5,
					"start":	20.000836,
					"end":	20.500189,
					"seconds":	0.49935299158096313,
					"bytes":	1310720,
					"bits_per_second":	20998692.661882009,
					"retransmits":	0,
					"snd_cwnd":	591300,
					"rtt":	50651,
					"rttvar":	129,
					"pmtu":	1500,
					"omitted":	false,
					"sender":	true
				}],
			"sum":	{
				"start":	20.000836,
				"end":	20.500189,
				"seconds":	0.49935299158096313,
				"bytes":	1310720,
				"bits_per_second":	20998692.661882009,
				"retransmits":	0,
				"omitted":	false,
				"sender":	true
			}
		}, {
			"streams":	[{
					"socket":	5,
					"start":	20.500189,
					"end":	21.000838,
					"seconds":	0.50064897537231445,
					"bytes":	0,
					"bits_per_second":	0,
					"retransmits":	0,
					"snd_cwnd":	597140,
					"rtt":	51046,
					"rttvar":	160,
					"pmtu":	1500,
					"omitted":	false,
					"sender":	true
				}],
			"sum":	{
				"start":	20.500189,
				"end":	21.000838,
				"seconds":	0.50064897537231445,
				"bytes":	0,
				"bits_per_second":	0,
				"retransmits":	0,
				"omitted":	false,
				"sender":	true
			}
		}, {
			"streams":	[{
					"socket":	5,
					"start":	21.000838,
					"end":	21.500474,
					"seconds":	0.49963599443435669,
					"bytes":	1310720,
					"bits_per_second":	20986798.623007622,
					"retransmits":	0,
					"snd_cwnd":	605900,
					"rtt":	50858,
					"rttvar":	482,
					"pmtu":	1500,
					"omitted":	false,
					"sender":	true
				}],
			"sum":	{
				"start":	21.000838,
				"end":	21.500474,
				"seconds":	0.49963599443435669,
				"bytes":	1310720,
				"bits_per_second":	20986798.623007622,
				"retransmits":	0,
				"omitted":	false,
				"sender":	true
			}
		}, {
			"streams":	[{
					"socket":	5,
					"start":	21.500474,
					"end":	22.002008,
					"seconds":	0.50153398513793945,
					"bytes":	0,
					"bits_per_second":	0,
					"retransmits":	0,
					"snd_cwnd":	614660,
					"rtt":	51534,
					"rttvar":	1162,
					"pmtu":	1500,
					"omitted":	false,
					"sender":	true
				}],
			"sum":	{
				"start":	21.500474,
				"end":	22.002008,
				"seconds":	0.50153398513793945,
				"bytes":	0,
				"bits_per_second":	0,
				"retransmits":	0,
				"omitted":	false,
				"sender":	true
			}
		}, {
			"streams":	[{
					"socket":	5,
					"start":	22.002008,
					"end":	22.500741,
					"seconds":	0.49873301386833191,
					"bytes":	0,
					"bits_per_second":	0,
					"retransmits":	0,
					"snd_cwnd":	614660,
					"rtt":	51715,
					"rttvar":	615,
					"pmtu":	1500,
					"omitted":	false,
					"sender":	true
				}],
			"sum":	{
				"start":	22.002008,
				"end":	22.500741,
				"seconds":	0.49873301386833191,
				"bytes":	0,
				"bits_per_second":	0,
				"retransmits":	0,
				"omitted":	false,
				"sender":	true
			}
		}, {
			"streams":	[{
					"socket":	5,
					"start":	22.500741,
					"end":	23.000862,
					"seconds":	0.500120997428894,
					"bytes":	1310720,
					"bits_per_second":	20966446.227826774,
					"retransmits":	0,
					"snd_cwnd":	623420,
					"rtt":	51723,
					"rttvar":	991,
					"pmtu":	1500,
					"omitted":	false,
					"sender":	true
				}],
			"sum":	{
				"start":	22.500741,
				"end":	23.000862,
				"seconds":	0.500120997428894,
				"bytes":	1310720,
				"bits_per_second":	20966446.227826774,
				"retransmits":	0,
				"omitted":	false,
				"sender":	true
			}
		}, {
			"streams":	[{
					"socket":	5,
					"start":	23.000862,
					"end":	23.500708,
					"seconds":	0.49984601140022278,
					"bytes":	0,
					"bits_per_second":	0,
					"retransmits":	0,
					"snd_cwnd":	629260,
					"rtt":	51172,
					"rttvar":	142,
					"pmtu":	1500,
					"omitted":	false,
					"sender":	true
				}],
			"sum":	{
				"start":	23.000862,
				"end":	23.500708,
				"seconds":	0.49984601140022278,
				"bytes":	0,
				"bits_per_second":	0,
				"retransmits":	0,
				"omitted":	false,
				"sender":	true
			}
		}, {
			"streams":	[{
					"socket":	5,
					"start":	23.500708,
					"end":	24.000568,
					"seconds":	0.49985998868942261,
					"bytes":	1310720,
					"bits_per_second":	20977394.144893449,
					"retransmits":	0,
					"snd_cwnd":	630720,
					"rtt":	51082,
					"rttvar":	56,
					"pmtu":	1500,
					"omitted":	false,
					"sender":	true
				}],
			"sum":	{
				"start":	23.500708,
				"end":	24.000568,
				"seconds":	0.49985998868942261,
				"bytes":	1310720,
				"bits_per_second":	20977394.144893449,
				"retransmits":	0,
				"omitted":	false,
				"sender":	true
			}
		}, {
			"streams":	[{
					"socket":	5,
					"start":	24.000568,
					"end":	24.500791,
					"seconds":	0.50022298097610474,
					"bytes":	0,
					"bits_per_second":	0,
					"retransmits":	0,
					"snd_cwnd":	633640,
					"rtt":	50975,
					"rttvar":	542,
					"pmtu":	1500,
					"omitted":	false,
					"sender":	true
				}],
			"sum":	{
				"start":	24.000568,
				"end":	24.500791,
				"seconds":	0.50022298097610474,
				"bytes":	0,
				"bits_per_second":	0,
				"retransmits":	0,
				"omitted":	false,
				"sender":	true
			}
		}, {
			"streams":	[{
					"socket":	5,
					"start":	24.500791,
					"end":	25.000467,
					"seconds":	0.499675989151001,
					"bytes":	1310720,
					"bits_per_second":	20985118.812325455,
					"retransmits":	0,
					"snd_cwnd":	640940,
					"rtt":	50706,
					"rttvar":	60,
					"pmtu":	1500,
					"omitted":	false,
					"sender":	true
				}],
			"sum":	{
				"start":	24.500791,
				"end":	25.000467,
				"seconds":	0.499675989151001,
				"bytes":	1310720,
				"bits_per_second":	20985118.812325455,
				"retransmits":	0,
				"omitted":	false,
				"sender":	true
			}
		}, {
			"streams":	[{
					"socket":	5,
					"start":	25.000467,
					"end":	25.500629,
					"seconds":	0.50016200542449951,
					"bytes":	0,
					"bits_per_second":	0,
					"retransmits":	0,
					"snd_cwnd":	648240,
					"rtt":	52047,
					"rttvar":	552,
					"pmtu":	1500,
					"omitted":	false,
					"sender":	true
				}],
			"sum":	{
				"start":	25.000467,
				"end":	25.500629,
				"seconds":	0.50016200542449951,
				"bytes":	0,
				"bits_per_second":	0,
				"retransmits":	0,
				"omitted":	false,
				"sender":	true
			}
		}, {
			"streams":	[{
					"socket":	5,
					"start":	25.500629,
					"end":	26.006964,
					"seconds":	0.50633502006530762,
					"bytes":	1310720,
					"bits_per_second":	20709134.435630258,
					"retransmits":	0,
					"snd_cwnd":	654080,
					"rtt":	50845,
					"rttvar":	268,
					"pmtu":	1500,
					"omitted":	false,
					"sender":	true
				}],
			"sum":	{
				"start":	25.500629,
				"end":	26.006964,
				"seconds":	0.50633502006530762,
				"bytes":	1310720,
				"bits_per_second":	20709134.435630258,
				"retransmits":	0,
				"omitted":	false,
				"sender":	true
			}
		}, {
			"streams":	[{
					"socket":	5,
					"start":	26.006964,
					"end":	26.50076,
					"seconds":	0.49379599094390869,
					"bytes":	0,
					"bits_per_second":	0,
					"retransmits":	0,
					"snd_cwnd":	667220,
					"rtt":	51092,
					"rttvar":	228,
					"pmtu":	1500,
					"omitted":	false,
					"sender":	true
				}],
			"sum":	{
				"start":	26.006964,
				"end":	26.50076,
				"seconds":	0.49379599094390869,
				"bytes":	0,
				"bits_per_second":	0,
				"retransmits":	0,
				"omitted":	false,
				"sender":	true
			}
		}, {
			"streams":	[{
					"socket":	5,
					"start":	26.50076,
					"end":	27.000432,
					"seconds":	0.499671995639801,
					"bytes":	1310720,
					"bits_per_second":	20985286.530964363,
					"retransmits":	0,
					"snd_cwnd":	675980,
					"rtt":	51431,
					"rttvar":	205,
					"pmtu":	1500,
					"omitted":	false,
					"sender":	true
				}],
			"sum":	{
				"start":	26.50076,
				"end":	27.000432,
				"seconds":	0.499671995639801,
				"bytes":	1310720,
				"bits_per_second":	20985286.530964363,
				"retransmits":	0,
				"omitted":	false,
				"sender":	true
			}
		}, {
			"streams":	[{
					"socket":	5,
					"start":	27.000432,
					"end":	27.500821,
					"seconds":	0.5003889799118042,
					"bytes":	0,
					"bits_per_second":	0,
					"retransmits":	0,
					"snd_cwnd":	686200,
					"rtt":	50936,
					"rttvar":	334,
					"pmtu":	1500,
					"omitted":	false,
					"sender":	true
				}],
			"sum":	{
				"start":	27.000432,
				"end":	27.500821,
				"seconds":	0.5003889799118042,
				"bytes":	0,
				"bits_per_second":	0,
				"retransmits":	0,
				"omitted":	false,
				"sender":	true
			}
		}, {
			"streams":	[{
					"socket":	5,
					"start":	27.500821,
					"end":	28.000364,
					"seconds":	0.499543011188507,
					"bytes":	1310720,
					"bits_per_second":	20990705.034692407,
					"retransmits":	0,
					"snd_cwnd":	692040,
					"rtt":	52701,
					"rttvar":	199,
					"pmtu":	1500,
					"omitted":	false,
					"sender":	true
				}],
			"sum":	{
				"start":	27.500821,
				"end":	28.000364,
				"seconds":	0.499543011188507,
				"bytes":	1310720,
				"bits_per_second":	20990705.034692407,
				"retransmits":	0,
				"omitted":	false,
				"sender":	true
			}
		}, {
			"streams":	[{
					"socket":	5,
					"start":	28.000364,
					"end":	28.500905,
					"seconds":	0.50054097175598145,
					"bytes":	0,
					"bits_per_second":	0,
					"retransmits":	0,
					"snd_cwnd":	702260,
					"rtt":	52126,
					"rttvar":	614,
					"pmtu":	1500,
					"omitted":	false,
					"sender":	true
				}],
			"sum":	{
				"start":	28.000364,
				"end":	28.500905,
				"seconds":	0.50054097175598145,
				"bytes":	0,
				"bits_per_second":	0,
				"retransmits":	0,
				"omitted":	false,
				"sender":	true
			}
		}, {
			"streams":	[{
					"socket":	5,
					"start":	28.500905,
					"end":	29.008915,
					"seconds":	0.50801002979278564,
					"bytes":	1310720,
					"bits_per_second":	20640852.316000693,
					"retransmits":	0,
					"snd_cwnd":	705180,
					"rtt":	53089,
					"rttvar":	209,
					"pmtu":	1500,
					"omitted":	false,
					"sender":	true
				}],
			"sum":	{
				"start":	28.500905,
				"end":	29.008915,
				"seconds":	0.50801002979278564,
				"bytes":	1310720,
				"bits_per_second":	20640852.316000693,
				"retransmits":	0,
				"omitted":	false,
				"sender":	true
			}
		}, {
			"streams":	[{
					"socket":	5,
					"start":	29.008915,
					"end":	29.500833,
					"seconds":	0.491917997598648,
					"bytes":	0,
					"bits_per_second":	0,
					"retransmits":	0,
					"snd_cwnd":	708100,
					"rtt":	54006,
					"rttvar":	256,
					"pmtu":	1500,
					"omitted":	false,
					"sender":	true
				}],
			"sum":	{
				"start":	29.008915,
				"end":	29.500833,
				"seconds":	0.491917997598648,
				"bytes":	0,
				"bits_per_second":	0,
				"retransmits":	0,
				"omitted":	false,
				"sender":	true
			}
		}, {
			"streams":	[{
					"socket":	5,
					"start":	29.500833,
					"end":	30.000972,
					"seconds":	0.50013899803161621,
					"bytes":	0,
					"bits_per_second":	0,
					"retransmits":	0,
					"snd_cwnd":	709560,
					"rtt":	52624,
					"rttvar":	201,
					"pmtu":	1500,
					"omitted":	false,
					"sender":	true
				}],
			"sum":	{
				"start":	29.500833,
				"end":	30.000972,
				"seconds":	0.50013899803161621,
				"bytes":	0,
				"bits_per_second":	0,
				"retransmits":	0,
				"omitted":	false,
				"sender":	true
			}
		}],
	"end":	{
		"streams":	[{
				"sender":	{
					"socket":	5,
					"start":	0,
					"end":	30.000972,
					"seconds":	30.000972,
					"bytes":	79953920,
					"bits_per_second":	21320354.553845789,
					"retransmits":	0,
					"max_snd_cwnd":	709560,
					"max_rtt":	68625,
					"min_rtt":	50476,
					"mean_rtt":	51803,
					"sender":	true
				},
				"receiver":	{
					"socket":	5,
					"start":	0,
					"end":	30.075606,
					"seconds":	30.000972,
					"bytes":	36951140,
					"bits_per_second":	9828866.6236683633,
					"sender":	true
				}
			}],
		"sum_sent":	{
			"start":	0,
			"end":	30.000972,
			"seconds":	30.000972,
			"bytes":	79953920,
			"bits_per_second":	21320354.553845789,
			"retransmits":	0,
			"sender":	true
		},
		"sum_received":	{
			"start":	0,
			"end":	30.075606,
			"seconds":	30.075606,
			"bytes":	36951140,
			"bits_per_second":	9828866.6236683633,
			"sender":	true
		},
		"cpu_utilization_percent":	{
			"host_total":	2.3264723563383876,
			"host_user":	0.024278112398832,
			"host_system":	2.3022140090242766,
			"remote_total":	1.3665007824284889,
			"remote_user":	0.04869567669184454,
			"remote_system":	1.3178081704780813
		},
		"sender_tcp_congestion":	"vegas",
		"receiver_tcp_congestion":	"cubic"
	}
}
